MANIFEST.in
setup.cfg
setup.py
versioneer.py
spylon/__init__.py
spylon/_version.py
spylon/common.py
spylon.egg-info/PKG-INFO
spylon.egg-info/SOURCES.txt
spylon.egg-info/dependency_links.txt
spylon.egg-info/requires.txt
spylon.egg-info/top_level.txt
spylon/simple/__init__.py
spylon/spark/__init__.py
spylon/spark/launcher.py
spylon/spark/progress.py
spylon/spark/spark_properties_1.6.0.json
spylon/spark/spark_properties_1.6.1.json
spylon/spark/spark_properties_2.0.2.json
spylon/spark/spark_properties_2.1.0.json
spylon/spark/spark_properties_latest.json
spylon/spark/utils.py
spylon/spark/yarn_launcher.py