Metadata-Version: 1.1
Name: spylon
Version: 0.2.12
Summary: Utilities to work with Scala/Java code with py4j
Home-page: https://github.com/maxpoint/spylon
Author: MaxPoint Interactive
Author-email: marius.vanniekerk@maxpoint.com
License: BSD 3-clause
Platform: UNKNOWN
Requires: six
